cloe_dbx_crawler/__init__.py
cloe_dbx_crawler/crawler.py
cloe_dbx_crawler/main.py
cloe_dbx_crawler/py.typed
cloe_dbx_crawler-0.2.0.dist-info/licenses/LICENSE
cloe_dbx_crawler-0.2.0.dist-info/WHEEL
cloe_dbx_crawler-0.2.0.dist-info/METADATA
cloe_dbx_crawler-0.2.0.dist-info/RECORD
