Metadata-Version: 2.4
Name: cloe-dbx-crawler
Version: 0.2.0
Summary: Crawls a Databricks workspace, extracts structured metadata from catalogs, schemas, and tables, and serializes it into the CLOE metadata format for downstream processing and integration.
Keywords: 
Author: initions
Author-email: initions <ICSMC_EXT_PYPIORG@accenture.com>
License-Expression: MIT
License-File: LICENSE
Classifier: Development Status :: 5 - Production/Stable
Classifier: Environment :: Console
Classifier: Intended Audience :: Developers
Classifier: Operating System :: OS Independent
Requires-Dist: cloe-dbx-connector~=1.0.0
Requires-Dist: cloe-logging>=0.3.7
Requires-Dist: cloe-metadata>=2.2.4
Requires-Dist: databricks-sdk~=0.41
Requires-Dist: pydantic~=2.10
Requires-Dist: typer~=0.15
Requires-Python: >=3.13, <3.14
